markdown_swiss/__init__.py
markdown_swiss/include.py
markdown_swiss-0.0.1.dist-info/DESCRIPTION.rst
markdown_swiss-0.0.1.dist-info/METADATA
markdown_swiss-0.0.1.dist-info/RECORD
markdown_swiss-0.0.1.dist-info/WHEEL
markdown_swiss-0.0.1.dist-info/metadata.json
markdown_swiss-0.0.1.dist-info/top_level.txt
