Metadata-Version: 2.0
Name: markdown-swiss
Version: 0.0.1
Summary: This is an extension to Python-Markdown which provides a variety of functions for running python code
Home-page: https://github.com/ChrisJefferson/markdown-swiss
Author: Chris Jefferson
Author-email: chris@bubblescope.net
License: UNKNOWN
Download-URL: https://github.com/ChrisJefferson/markdown-swiss/tarball/v0.0.1
Keywords: Markdown,typesetting,include,plugin,extension
Platform: UNKNOWN
Classifier: Development Status :: 3 - Alpha
Classifier: Intended Audience :: Developers
Classifier: Topic :: Internet :: WWW/HTTP :: Site Management
Classifier: Topic :: Software Development :: Documentation
Classifier: Topic :: Software Development :: Libraries :: Python Modules
Classifier: Topic :: Text Processing :: Filters
Classifier: Topic :: Text Processing :: Markup :: HTML
Classifier: License :: OSI Approved :: GNU General Public License v3 (GPLv3)
Classifier: Programming Language :: Python :: 2
Classifier: Programming Language :: Python :: 2.7
Requires-Dist: markdown
